feedx/__init__.py
feedx/conftest.py
feedx/data_preparation.py
feedx/data_preparation_test.py
feedx/experiment_analysis.py
feedx/experiment_analysis_test.py
feedx/experiment_design.py
feedx/experiment_design_test.py
feedx/experiment_simulations.py
feedx/experiment_simulations_test.py
feedx/plotting.py
feedx/plotting_test.py
feedx/statistics.py
feedx/statistics_test.py
feedx-0.1.2.dist-info/licenses/LICENSE
feedx-0.1.2.dist-info/METADATA
feedx-0.1.2.dist-info/WHEEL
feedx-0.1.2.dist-info/top_level.txt
feedx-0.1.2.dist-info/RECORD
